zkauth/__init__.py
zkauth/client.py
zkauth/exceptions.py
zkauth/models.py
zkauth/integrations/__init__.py
zkauth/integrations/django.py
zkauth/integrations/fastapi.py
zkauth_sdk-1.3.0.dist-info/METADATA
zkauth_sdk-1.3.0.dist-info/WHEEL
zkauth_sdk-1.3.0.dist-info/top_level.txt
zkauth_sdk-1.3.0.dist-info/RECORD
