Metadata-Version: 2.4
Name: zkauth-sdk
Version: 1.3.0
Summary: Zero-knowledge proof authentication SDK for Python
Home-page: https://github.com/zkauth/zkauth-developer-platform
Author: ZKAuth Team
Author-email: ZKAuth Team <support@zkauth.com>
Project-URL: Homepage, https://github.com/zkauth/zkauth-developer-platform
Project-URL: Documentation, https://docs.zkauth.com
Project-URL: Repository, https://github.com/zkauth/zkauth-developer-platform.git
Project-URL: Bug Tracker, https://github.com/zkauth/zkauth-developer-platform/issues
Keywords: zkauth,zero-knowledge,authentication,cryptography,privacy,zk-snarks
Classifier: Development Status :: 5 - Production/Stable
Classifier: Intended Audience :: Developers
Classifier: License :: OSI Approved :: MIT License
Classifier: Operating System :: OS Independent
Classifier: Programming Language :: Python :: 3
Classifier: Programming Language :: Python :: 3.8
Classifier: Programming Language :: Python :: 3.9
Classifier: Programming Language :: Python :: 3.10
Classifier: Programming Language :: Python :: 3.11
Classifier: Programming Language :: Python :: 3.12
Classifier: Topic :: Security :: Cryptography
Classifier: Topic :: Software Development :: Libraries :: Python Modules
Requires-Python: >=3.8
Requires-Dist: httpx>=0.25.0
Requires-Dist: cryptography>=41.0.0
Requires-Dist: pydantic>=2.0.0
Requires-Dist: typing-extensions>=4.0.0
Provides-Extra: django
Requires-Dist: django>=3.2; extra == "django"
Provides-Extra: fastapi
Requires-Dist: fastapi>=0.100.0; extra == "fastapi"
Provides-Extra: dev
Requires-Dist: pytest>=7.0.0; extra == "dev"
Requires-Dist: pytest-asyncio>=0.21.0; extra == "dev"
Requires-Dist: pytest-cov>=4.0.0; extra == "dev"
Requires-Dist: black>=23.0.0; extra == "dev"
Requires-Dist: isort>=5.12.0; extra == "dev"
Requires-Dist: mypy>=1.5.0; extra == "dev"
Requires-Dist: pre-commit>=3.0.0; extra == "dev"
Dynamic: author
Dynamic: home-page
Dynamic: requires-python
